artifactory.py
dohq_artifactory/__init__.py
dohq_artifactory/admin.py
dohq_artifactory/auth.py
dohq_artifactory/compat.py
dohq_artifactory/exception.py
dohq_artifactory/logger.py
dohq_artifactory-1.0.1.dist-info/LICENSE
dohq_artifactory-1.0.1.dist-info/METADATA
dohq_artifactory-1.0.1.dist-info/WHEEL
dohq_artifactory-1.0.1.dist-info/top_level.txt
dohq_artifactory-1.0.1.dist-info/RECORD
